Dockerfile
LICENSE
MANIFEST.in
Makefile
NEWS.rst
README.rst
requirements.txt
setup.cfg
setup.py
./Dockerfile
./LICENSE
./Makefile
./NEWS.rst
./README.rst
docs/Makefile
docs/conf.py
docs/discoursegraphs.rst
docs/history.rst
docs/index.rst
docs/make.bat
docs/modules.rst
docs/readme.rst
src/discoursegraphs/__init__.py
src/discoursegraphs/corpora.py
src/discoursegraphs/discoursegraph.py
src/discoursegraphs/merging.py
src/discoursegraphs/relabel.py
src/discoursegraphs/statistics.py
src/discoursegraphs/util.py
src/discoursegraphs.egg-info/PKG-INFO
src/discoursegraphs.egg-info/SOURCES.txt
src/discoursegraphs.egg-info/dependency_links.txt
src/discoursegraphs.egg-info/entry_points.txt
src/discoursegraphs.egg-info/not-zip-safe
src/discoursegraphs.egg-info/requires.txt
src/discoursegraphs.egg-info/top_level.txt
src/discoursegraphs/data/urml-base.dtd
src/discoursegraphs/data/potsdam-commentary-corpus-2.0.0/coreference/basedata/words.dtd
src/discoursegraphs/data/potsdam-commentary-corpus-2.0.0/coreference/markables/markables.dtd
src/discoursegraphs/readwrite/__init__.py
src/discoursegraphs/readwrite/anaphoricity.py
src/discoursegraphs/readwrite/brackets.py
src/discoursegraphs/readwrite/brat.py
src/discoursegraphs/readwrite/conano.py
src/discoursegraphs/readwrite/conll.py
src/discoursegraphs/readwrite/decour.py
src/discoursegraphs/readwrite/dot.py
src/discoursegraphs/readwrite/exmaralda.py
src/discoursegraphs/readwrite/exportxml.py
src/discoursegraphs/readwrite/freqt.py
src/discoursegraphs/readwrite/generic.py
src/discoursegraphs/readwrite/geoff.py
src/discoursegraphs/readwrite/gexf.py
src/discoursegraphs/readwrite/graphml.py
src/discoursegraphs/readwrite/mmax2.py
src/discoursegraphs/readwrite/neo4j.py
src/discoursegraphs/readwrite/ptb.py
src/discoursegraphs/readwrite/tiger.py
src/discoursegraphs/readwrite/tree.py
src/discoursegraphs/readwrite/paulaxml/__init__.py
src/discoursegraphs/readwrite/paulaxml/paula.py
src/discoursegraphs/readwrite/paulaxml/paula_feat.dtd
src/discoursegraphs/readwrite/paulaxml/paula_header.dtd
src/discoursegraphs/readwrite/paulaxml/paula_mark.dtd
src/discoursegraphs/readwrite/paulaxml/paula_multiFeat.dtd
src/discoursegraphs/readwrite/paulaxml/paula_rel.dtd
src/discoursegraphs/readwrite/paulaxml/paula_struct.dtd
