Metadata-Version: 1.0
Name: discoursegraphs
Version: 0.4.12
Summary: graph-based processing of multi-level annotated corpora
Home-page: https://github.com/arne-cl/discoursegraphs
Author: Arne Neumann
Author-email: discoursegraphs.programming@arne.cl
License: 3-Clause BSD License
Keywords: corpus linguistics nlp graph networkx annotation
Platform: UNKNOWN
